mdf_helper/__init__.py
mdf_helper/my_lib.py
pkg/__init__.py
pkg/my_lib.py
mdfreader_helper-0.0.1.dist-info/LICENSE
mdfreader_helper-0.0.1.dist-info/METADATA
mdfreader_helper-0.0.1.dist-info/WHEEL
mdfreader_helper-0.0.1.dist-info/top_level.txt
mdfreader_helper-0.0.1.dist-info/RECORD
