Metadata-Version: 2.1
Name: mdfreader-helper
Version: 0.0.1
Summary: Extention to the python lib 'mdfreader', for finding/parsing/preprocessing the data from .dat/.mdf files
Home-page: https://github.com/Siuuuu7/mdfreader-helper
Author: H.Yu
Author-email: haoyang_yu123@yahoo.com
License: UNKNOWN
Platform: UNKNOWN
Classifier: Programming Language :: Python :: 3
Classifier: License :: OSI Approved :: Apache Software License
Classifier: Operating System :: OS Independent
Requires-Python: >=3.6
